mdsa/__init__.py
mdsa/__main__.py
mdsa/async_/__init__.py
mdsa/async_/executor.py
mdsa/async_/manager.py
mdsa/auth/__init__.py
mdsa/auth/jwt_auth.py
mdsa/cli/__init__.py
mdsa/cli/commands.py
mdsa/communication/__init__.py
mdsa/config/__init__.py
mdsa/config/mdsa_config.json
mdsa/config/platform_detector.py
mdsa/config/ports.py
mdsa/core/__init__.py
mdsa/core/app_registry.py
mdsa/core/communication_bus.py
mdsa/core/complexity_analyzer.py
mdsa/core/orchestrator.py
mdsa/core/reasoner.py
mdsa/core/router.py
mdsa/core/state_machine.py
mdsa/domains/__init__.py
mdsa/domains/config.py
mdsa/domains/executor.py
mdsa/domains/model_validator.py
mdsa/domains/prompts.py
mdsa/domains/registry.py
mdsa/domains/validator.py
mdsa/integrations/__init__.py
mdsa/integrations/adapters/__init__.py
mdsa/integrations/adapters/ollama_adapter.py
mdsa/integrations/tools/__init__.py
mdsa/memory/__init__.py
mdsa/memory/dual_rag.py
mdsa/models/__init__.py
mdsa/models/config.py
mdsa/models/loader.py
mdsa/models/manager.py
mdsa/models/registry.py
mdsa/models/loaders/__init__.py
mdsa/monitoring/__init__.py
mdsa/monitoring/logger.py
mdsa/monitoring/metrics.py
mdsa/monitoring/service.py
mdsa/rag/__init__.py
mdsa/tools/__init__.py
mdsa/tools/base.py
mdsa/tools/builtin.py
mdsa/tools/encryption.py
mdsa/tools/manager.py
mdsa/tools/registry.py
mdsa/tools/smart_executor.py
mdsa/ui/__init__.py
mdsa/ui/auth.py
mdsa/ui/enhanced_dashboard.py
mdsa/ui/dashboard/__init__.py
mdsa/ui/dashboard/app.py
mdsa/ui/dashboard/static/css/dashboard.css
mdsa/ui/dashboard/static/js/visualizations.js
mdsa/ui/dashboard/templates/admin_models.html
mdsa/ui/dashboard/templates/admin_rag.html
mdsa/ui/dashboard/templates/admin_tools.html
mdsa/ui/dashboard/templates/domains.html
mdsa/ui/dashboard/templates/login.html
mdsa/ui/dashboard/templates/models.html
mdsa/ui/dashboard/templates/monitor.html
mdsa/ui/dashboard/templates/rag.html
mdsa/ui/dashboard/templates/welcome.html
mdsa/ui/static/css/style.css
mdsa/ui/static/js/common.js
mdsa_framework-1.0.6.dist-info/licenses/LICENSE
mdsa_framework-1.0.6.dist-info/METADATA
mdsa_framework-1.0.6.dist-info/WHEEL
mdsa_framework-1.0.6.dist-info/top_level.txt
mdsa_framework-1.0.6.dist-info/RECORD
