Metadata-Version: 2.4
Name: mdsa-framework
Version: 1.0.6
Summary: Domain-agnostic AI orchestration framework for e-commerce, healthcare, HR, finance, and custom domains
Home-page: https://github.com/yourusername/mdsa
Author: MDSA Team
Author-email: Vicky Vignesh <vickyvignesh2002@gmail.com>
License: Apache 2.0
Project-URL: Homepage, https://github.com/VickyVignesh2002/MDSA-Orchestration-Framework
Project-URL: Documentation, https://github.com/VickyVignesh2002/MDSA-Orchestration-Framework#readme
Project-URL: Repository, https://github.com/VickyVignesh2002/MDSA-Orchestration-Framework
Project-URL: Bug Tracker, https://github.com/VickyVignesh2002/MDSA-Orchestration-Framework/issues
Keywords: ai,machine-learning,nlp,orchestration,slm,small-language-models,rag,multi-domain,domain-agnostic,cross-domain,ecommerce,healthcare,hr,finance,customer-support,tinybert,routing,chatbot,intelligent-agents,enterprise-ai,semantic-classification
Classifier: Development Status :: 4 - Beta
Classifier: Intended Audience :: Developers
Classifier: Intended Audience :: Science/Research
Classifier: Intended Audience :: Financial and Insurance Industry
Classifier: Intended Audience :: Healthcare Industry
Classifier: Intended Audience :: Customer Service
Classifier: Topic :: Scientific/Engineering :: Artificial Intelligence
Classifier: Topic :: Office/Business
Classifier: Topic :: Software Development :: Libraries :: Application Frameworks
Classifier: License :: OSI Approved :: Apache Software License
Classifier: Programming Language :: Python :: 3
Classifier: Programming Language :: Python :: 3.9
Classifier: Programming Language :: Python :: 3.10
Classifier: Programming Language :: Python :: 3.11
Classifier: Programming Language :: Python :: 3.12
Requires-Python: >=3.8
License-File: LICENSE
Requires-Dist: torch>=2.0.0
Requires-Dist: transformers>=4.35.0
Requires-Dist: sentence-transformers>=2.2.2
Requires-Dist: accelerate>=0.24.0
Requires-Dist: peft>=0.6.0
Requires-Dist: chromadb>=0.4.18
Requires-Dist: fastapi>=0.104.0
Requires-Dist: uvicorn[standard]>=0.24.0
Requires-Dist: websockets>=11.0
Requires-Dist: pyyaml>=6.0
Requires-Dist: aiohttp>=3.9.0
Requires-Dist: cryptography>=41.0.0
Requires-Dist: psutil>=5.9.0
Requires-Dist: pydantic>=2.5.0
Requires-Dist: prometheus-client>=0.17.0
Requires-Dist: requests>=2.31.0
Requires-Dist: tqdm>=4.65.0
Requires-Dist: numpy>=1.24.0
Requires-Dist: python-multipart>=0.0.6
Requires-Dist: jinja2>=3.1.2
Requires-Dist: flask>=3.0.0
Requires-Dist: flask-login>=0.6.3
Requires-Dist: flask-limiter>=3.5.0
Requires-Dist: werkzeug>=3.0.0
Requires-Dist: python-dotenv>=1.0.0
Requires-Dist: aiofiles>=23.2.0
Requires-Dist: pyjwt>=2.8.0
Requires-Dist: bcrypt>=4.0.0
Requires-Dist: pypdf>=4.0.0
Requires-Dist: openpyxl>=3.1.0
Provides-Extra: dev
Requires-Dist: pytest>=7.4.0; extra == "dev"
Requires-Dist: pytest-asyncio>=0.21.0; extra == "dev"
Requires-Dist: pytest-cov>=4.1.0; extra == "dev"
Requires-Dist: pytest-mock>=3.12.0; extra == "dev"
Requires-Dist: black>=23.7.0; extra == "dev"
Requires-Dist: flake8>=6.1.0; extra == "dev"
Requires-Dist: mypy>=1.5.0; extra == "dev"
Requires-Dist: isort>=5.12.0; extra == "dev"
Requires-Dist: pre-commit>=3.5.0; extra == "dev"
Provides-Extra: gpu
Requires-Dist: bitsandbytes>=0.41.0; extra == "gpu"
Provides-Extra: faiss
Requires-Dist: faiss-cpu>=1.7.4; extra == "faiss"
Provides-Extra: faiss-gpu
Requires-Dist: faiss-gpu>=1.7.4; extra == "faiss-gpu"
Provides-Extra: pinecone
Requires-Dist: pinecone-client>=2.2.0; extra == "pinecone"
Provides-Extra: docs
Requires-Dist: mkdocs>=1.5.0; extra == "docs"
Requires-Dist: mkdocs-material>=9.4.0; extra == "docs"
Requires-Dist: mkdocstrings[python]>=0.23.0; extra == "docs"
Dynamic: author
Dynamic: home-page
Dynamic: license-file
Dynamic: requires-python
